brainways/__init__.py
brainways/_version.py
brainways/conftest.py
brainways/napari.yaml
brainways/elastix/Par0033bspline.txt
brainways/elastix/Par0033similarity.txt
brainways/elastix/__init__.py
brainways/elastix/elastix.py
brainways/elastix/_tests/test_elastix.py
brainways/model/model_utils.py
brainways/model/siamese/__init__.py
brainways/model/siamese/siamese_backbone.py
brainways/model/siamese/siamese_model.py
brainways/model/transforms/__init__.py
brainways/model/transforms/normalize_percentile.py
brainways/pipeline/__init__.py
brainways/pipeline/affine_2d.py
brainways/pipeline/atlas_registration.py
brainways/pipeline/brainways_params.py
brainways/pipeline/brainways_pipeline.py
brainways/pipeline/cell_detector.py
brainways/pipeline/tps.py
brainways/pipeline/_tests/test_atlas_registration.py
brainways/pipeline/_tests/test_brainways_pipeline.py
brainways/pipeline/_tests/test_cell_detector.py
brainways/project/__init__.py
brainways/project/_utils.py
brainways/project/brainways_project.py
brainways/project/brainways_subject.py
brainways/project/info_classes.py
brainways/project/_tests/__init__.py
brainways/project/_tests/conftest.py
brainways/project/_tests/test_brainways_project.py
brainways/project/_tests/test_brainways_subject.py
brainways/project/_tests/test_utils.py
brainways/project/_tests/test_projects/v0.1.1/project.bwp
brainways/project/_tests/test_projects/v0.1.1/subject1/brainways.bin
brainways/project/_tests/test_projects/v0.1.4/project.bwp
brainways/project/_tests/test_projects/v0.1.4/subject1/brainways.bin
brainways/project/_tests/test_projects/v0.1.5/project.bwp
brainways/project/_tests/test_projects/v0.1.5/subject1/brainways.bin
brainways/resources/sample_image.jpg
brainways/scripts/__init__.py
brainways/scripts/batch_create_thumbnails.py
brainways/scripts/cli.py
brainways/scripts/create_excel.py
brainways/scripts/create_excel_colabelling.py
brainways/scripts/create_reg_model_data.py
brainways/scripts/import_cell_detections_keren.py
brainways-0.1.16.3.dist-info/licenses/LICENSE
brainways-0.1.16.3.dist-info/METADATA
brainways-0.1.16.3.dist-info/WHEEL
brainways-0.1.16.3.dist-info/entry_points.txt
brainways-0.1.16.3.dist-info/top_level.txt
brainways-0.1.16.3.dist-info/RECORD
