Metadata-Version: 2.4
Name: brainways
Version: 0.1.16.3
Summary: Brainways
Home-page: https://github.com/bkntr/brainways
Author: Ben Kantor
Author-email: benkantor@mail.tau.ac.il
License: GPL-3.0
Project-URL: Bug Tracker, https://github.com/bkntr/brainways/issues
Project-URL: Documentation, https://github.com/bkntr/brainways#README.md
Project-URL: Source Code, https://github.com/bkntr/brainways
Project-URL: User Support, https://github.com/bkntr/brainways/issues
Classifier: Development Status :: 2 - Pre-Alpha
Classifier: Framework :: napari
Classifier: Intended Audience :: Developers
Classifier: License :: OSI Approved :: GNU General Public License v3 (GPLv3)
Classifier: Operating System :: OS Independent
Classifier: Programming Language :: Python
Classifier: Programming Language :: Python :: 3
Classifier: Programming Language :: Python :: 3 :: Only
Classifier: Programming Language :: Python :: 3.9
Classifier: Programming Language :: Python :: 3.10
Classifier: Programming Language :: Python :: 3.11
Classifier: Programming Language :: Python :: 3.12
Classifier: Programming Language :: Python :: Implementation :: CPython
Classifier: Topic :: Scientific/Engineering :: Image Processing
Requires-Python: >=3.9
License-File: LICENSE
Requires-Dist: aicsimageio[base-imageio]==4.14.0
Requires-Dist: aicspylibczi
Requires-Dist: brainglobe-atlasapi
Requires-Dist: click
Requires-Dist: dacite
Requires-Dist: datasets
Requires-Dist: fsspec
Requires-Dist: huggingface-hub
Requires-Dist: importlib-resources
Requires-Dist: itk-elastix
Requires-Dist: kornia
Requires-Dist: napari[all]>=0.5.0
Requires-Dist: natsort
Requires-Dist: networkx
Requires-Dist: numpy<2.0.0
Requires-Dist: opencv-contrib-python-headless
Requires-Dist: opencv-python-headless
Requires-Dist: openpyxl
Requires-Dist: pandas
Requires-Dist: paquo
Requires-Dist: qtpy
Requires-Dist: scikit-image
Requires-Dist: scikit-learn
Requires-Dist: scikit-posthocs
Requires-Dist: stardist
Requires-Dist: statsmodels
Requires-Dist: tensorflow<2.20
Requires-Dist: toml
Requires-Dist: torch
Requires-Dist: torchvision
Requires-Dist: lightning
Requires-Dist: tqdm
Requires-Dist: scyjava
Requires-Dist: jpype1==1.5.0
Requires-Dist: albumentations==2.0.5
Requires-Dist: jsonargparse<5.0.0,>=4.0.0
Requires-Dist: timm<2.0.0,>=1.0.0
Provides-Extra: dev
Requires-Dist: pre-commit; extra == "dev"
Requires-Dist: scipy-stubs; extra == "dev"
Provides-Extra: testing
Requires-Dist: py; extra == "testing"
Requires-Dist: pyqt5; extra == "testing"
Requires-Dist: pytest; extra == "testing"
Requires-Dist: pytest-cov; extra == "testing"
Requires-Dist: pytest-mock; extra == "testing"
Requires-Dist: pytest-qt<4.1.0; extra == "testing"
Requires-Dist: tox; extra == "testing"
Dynamic: license-file
